{
    "Position": 0,
    "Index": 0,
    "Name": "tomb_of_the_demon_priest.RDB",
    "Type": "Rdb",
    "RmbBlock": {
        "FldHeader": {
            "NumBlockDataRecords": 0,
            "NumMisc3dObjectRecords": 0,
            "NumMiscFlatObjectRecords": 0,
            "BlockPositions": null,
            "BuildingDataList": null,
            "BlockDataSizes": null,
            "GroundData": {},
            "AutoMapData": null,
            "Name": null,
            "OtherNames": null
        },
        "SubRecords": null,
        "Misc3dObjectRecords": null,
        "MiscFlatObjectRecords": null
    },
    "RdbBlock": {
        "ModelReferenceList": [
            {
                "ModelId": "850004",
                "ModelIdNum": 850004,
                "Description": "XXX"
            },
            {
                "ModelId": "70300",
                "ModelIdNum": 70300,
                "Description": "EXT"
            },
            {
                "ModelId": "55005",
                "ModelIdNum": 55005,
                "Description": "DOR"
            }
        ],
        "ObjectRootList": [
            {
                "RdbObjects": [
                    {
                        "Position": 66580,
                        "Index": 0,
                        "XPos": 50,
                        "YPos": 0,
                        "ZPos": 50,
                        "Type": "Model",
                        "Resources": {
                            "ModelResource": {
                                "XRotation": 0,
                                "YRotation": 0,
                                "ZRotation": 0,
                                "ModelIndex": 0,
                                "TriggerFlag_StartingLock": 0,
                                "SoundIndex": 0,
                                "ActionResource": {
                                    "Position": 0,
                                    "Axis": 0,
                                    "Duration": 0,
                                    "Magnitude": 0,
                                    "NextObjectOffset": 0,
                                    "PreviousObjectOffset": 0,
                                    "NextObjectIndex": 0,
                                    "Flags": 0
                                }
                            }
                        }
                    },
                    {
                        "Position": 94516,
                        "Index": 1,
                        "XPos": 0,
                        "YPos": 0,
                        "ZPos": 0,
                        "Type": "Model",
                        "Resources": {
                            "ModelResource": {
                                "XRotation": 0,
                                "YRotation": 1536,
                                "ZRotation": 0,
                                "ModelIndex": 1,
                                "TriggerFlag_StartingLock": 0,
                                "SoundIndex": 0,
                                "ActionResource": {
                                    "Position": 0,
                                    "Axis": 0,
                                    "Duration": 0,
                                    "Magnitude": 0,
                                    "NextObjectOffset": 0,
                                    "PreviousObjectOffset": 0,
                                    "NextObjectIndex": 0,
                                    "Flags": 0
                                }
                            }
                        }
                    },
                    {
                        "Position": 38028,
                        "Index": 2,
                        "XPos": 0,
                        "YPos": 0,
                        "ZPos": 100,
                        "Type": "Flat",
                        "Resources": {
                            "FlatResource": {
                                "Position": 0,
                                "TextureArchive": 199,
                                "TextureRecord": 10,
                                "Flags": 0,
                                "Magnitude": 0,
                                "SoundIndex": 0,
                                "FactionOrMobileId": 0,
                                "NextObjectOffset": 0,
                                "Action": 0,
                                "IsCustomData": false
                            }
                        }
                    },
                    {
                        "Position": 27005,
                        "Index": 3,
                        "XPos": -300,
                        "YPos": 0,
                        "ZPos": 124,
                        "Type": "Model",
                        "Resources": {
                            "ModelResource": {
                                "XRotation": 0,
                                "YRotation": 1536,
                                "ZRotation": 0,
                                "ModelIndex": 2,
                                "TriggerFlag_StartingLock": 0,
                                "SoundIndex": 70,
                                "ActionResource": {
                                    "Position": 0,
                                    "Axis": 0,
                                    "Duration": 0,
                                    "Magnitude": 0,
                                    "NextObjectOffset": 0,
                                    "PreviousObjectOffset": -1,
                                    "NextObjectIndex": 0,
                                    "Flags": 16
                                }
                            }
                        }
                    },
                    {
                        "Position": 21171,
                        "Index": 4,
                        "XPos": 300,
                        "YPos": 0,
                        "ZPos": 76,
                        "Type": "Model",
                        "Resources": {
                            "ModelResource": {
                                "XRotation": 0,
                                "YRotation": 512,
                                "ZRotation": 0,
                                "ModelIndex": 2,
                                "TriggerFlag_StartingLock": 0,
                                "SoundIndex": 70,
                                "ActionResource": {
                                    "Position": 0,
                                    "Axis": 0,
                                    "Duration": 0,
                                    "Magnitude": 0,
                                    "NextObjectOffset": 0,
                                    "PreviousObjectOffset": -1,
                                    "NextObjectIndex": 0,
                                    "Flags": 16
                                }
                            }
                        }
                    },
                    {
                        "Position": 22020,
                        "Index": 5,
                        "XPos": -424,
                        "YPos": 0,
                        "ZPos": 400,
                        "Type": "Model",
                        "Resources": {
                            "ModelResource": {
                                "XRotation": 0,
                                "YRotation": 0,
                                "ZRotation": 0,
                                "ModelIndex": 2,
                                "TriggerFlag_StartingLock": 0,
                                "SoundIndex": 70,
                                "ActionResource": {
                                    "Position": 0,
                                    "Axis": 0,
                                    "Duration": 0,
                                    "Magnitude": 0,
                                    "NextObjectOffset": 0,
                                    "PreviousObjectOffset": -1,
                                    "NextObjectIndex": 0,
                                    "Flags": 16
                                }
                            }
                        }
                    },
                    {
                        "Position": 22021,
                        "Index": 6,
                        "XPos": -376,
                        "YPos": 0,
                        "ZPos": -200,
                        "Type": "Model",
                        "Resources": {
                            "ModelResource": {
                                "XRotation": 0,
                                "YRotation": 1024,
                                "ZRotation": 0,
                                "ModelIndex": 2,
                                "TriggerFlag_StartingLock": 0,
                                "SoundIndex": 70,
                                "ActionResource": {
                                    "Position": 0,
                                    "Axis": 0,
                                    "Duration": 0,
                                    "Magnitude": 0,
                                    "NextObjectOffset": 0,
                                    "PreviousObjectOffset": -1,
                                    "NextObjectIndex": 0,
                                    "Flags": 16
                                }
                            }
                        }
                    },
                    {
                        "Position": 11369,
                        "Index": 7,
                        "XPos": 376,
                        "YPos": 0,
                        "ZPos": 400,
                        "Type": "Model",
                        "Resources": {
                            "ModelResource": {
                                "XRotation": 0,
                                "YRotation": 0,
                                "ZRotation": 0,
                                "ModelIndex": 2,
                                "TriggerFlag_StartingLock": 0,
                                "SoundIndex": 70,
                                "ActionResource": {
                                    "Position": 0,
                                    "Axis": 0,
                                    "Duration": 0,
                                    "Magnitude": 0,
                                    "NextObjectOffset": 0,
                                    "PreviousObjectOffset": -1,
                                    "NextObjectIndex": 0,
                                    "Flags": 16
                                }
                            }
                        }
                    },
                    {
                        "Position": 10035,
                        "Index": 8,
                        "XPos": 424,
                        "YPos": 0,
                        "ZPos": -200,
                        "Type": "Model",
                        "Resources": {
                            "ModelResource": {
                                "XRotation": 0,
                                "YRotation": 1024,
                                "ZRotation": 0,
                                "ModelIndex": 2,
                                "TriggerFlag_StartingLock": 0,
                                "SoundIndex": 70,
                                "ActionResource": {
                                    "Position": 0,
                                    "Axis": 0,
                                    "Duration": 0,
                                    "Magnitude": 0,
                                    "NextObjectOffset": 0,
                                    "PreviousObjectOffset": -1,
                                    "NextObjectIndex": 0,
                                    "Flags": 16
                                }
                            }
                        }
                    },
                    {
                        "Position": 15940,
                        "Index": 9,
                        "XPos": -376,
                        "YPos": 0,
                        "ZPos": -800,
                        "Type": "Model",
                        "Resources": {
                            "ModelResource": {
                                "XRotation": 0,
                                "YRotation": 1024,
                                "ZRotation": 0,
                                "ModelIndex": 2,
                                "TriggerFlag_StartingLock": 0,
                                "SoundIndex": 70,
                                "ActionResource": {
                                    "Position": 0,
                                    "Axis": 0,
                                    "Duration": 0,
                                    "Magnitude": 0,
                                    "NextObjectOffset": 0,
                                    "PreviousObjectOffset": -1,
                                    "NextObjectIndex": 0,
                                    "Flags": 16
                                }
                            }
                        }
                    },
                    {
                        "Position": 28672,
                        "Index": 10,
                        "XPos": 300,
                        "YPos": 0,
                        "ZPos": -576,
                        "Type": "Model",
                        "Resources": {
                            "ModelResource": {
                                "XRotation": 0,
                                "YRotation": 1536,
                                "ZRotation": 0,
                                "ModelIndex": 2,
                                "TriggerFlag_StartingLock": 0,
                                "SoundIndex": 70,
                                "ActionResource": {
                                    "Position": 0,
                                    "Axis": 0,
                                    "Duration": 0,
                                    "Magnitude": 0,
                                    "NextObjectOffset": 0,
                                    "PreviousObjectOffset": -1,
                                    "NextObjectIndex": 0,
                                    "Flags": 16
                                }
                            }
                        }
                    },
                    {
                        "Position": 19969,
                        "Index": 11,
                        "XPos": 500,
                        "YPos": 0,
                        "ZPos": -624,
                        "Type": "Model",
                        "Resources": {
                            "ModelResource": {
                                "XRotation": 0,
                                "YRotation": 512,
                                "ZRotation": 0,
                                "ModelIndex": 2,
                                "TriggerFlag_StartingLock": 0,
                                "SoundIndex": 70,
                                "ActionResource": {
                                    "Position": 0,
                                    "Axis": 0,
                                    "Duration": 0,
                                    "Magnitude": 0,
                                    "NextObjectOffset": 0,
                                    "PreviousObjectOffset": -1,
                                    "NextObjectIndex": 0,
                                    "Flags": 16
                                }
                            }
                        }
                    },
                    {
                        "Position": 19600,
                        "Index": 12,
                        "XPos": 424,
                        "YPos": 0,
                        "ZPos": -800,
                        "Type": "Model",
                        "Resources": {
                            "ModelResource": {
                                "XRotation": 0,
                                "YRotation": 1024,
                                "ZRotation": 0,
                                "ModelIndex": 2,
                                "TriggerFlag_StartingLock": 0,
                                "SoundIndex": 70,
                                "ActionResource": {
                                    "Position": 0,
                                    "Axis": 0,
                                    "Duration": 0,
                                    "Magnitude": 0,
                                    "NextObjectOffset": 0,
                                    "PreviousObjectOffset": -1,
                                    "NextObjectIndex": 0,
                                    "Flags": 16
                                }
                            }
                        }
                    },
                    {
                        "Position": 16830,
                        "Index": 13,
                        "XPos": 576,
                        "YPos": 0,
                        "ZPos": -400,
                        "Type": "Model",
                        "Resources": {
                            "ModelResource": {
                                "XRotation": 0,
                                "YRotation": 0,
                                "ZRotation": 0,
                                "ModelIndex": 2,
                                "TriggerFlag_StartingLock": 0,
                                "SoundIndex": 70,
                                "ActionResource": {
                                    "Position": 0,
                                    "Axis": 0,
                                    "Duration": 0,
                                    "Magnitude": 0,
                                    "NextObjectOffset": 0,
                                    "PreviousObjectOffset": -1,
                                    "NextObjectIndex": 0,
                                    "Flags": 16
                                }
                            }
                        }
                    },
                    {
                        "Position": 12858,
                        "Index": 14,
                        "XPos": 500,
                        "YPos": 0,
                        "ZPos": -1324,
                        "Type": "Model",
                        "Resources": {
                            "ModelResource": {
                                "XRotation": 0,
                                "YRotation": 512,
                                "ZRotation": 0,
                                "ModelIndex": 2,
                                "TriggerFlag_StartingLock": 0,
                                "SoundIndex": 70,
                                "ActionResource": {
                                    "Position": 0,
                                    "Axis": 0,
                                    "Duration": 0,
                                    "Magnitude": 0,
                                    "NextObjectOffset": 0,
                                    "PreviousObjectOffset": -1,
                                    "NextObjectIndex": 0,
                                    "Flags": 16
                                }
                            }
                        }
                    },
                    {
                        "Position": 17636,
                        "Index": 15,
                        "XPos": 224,
                        "YPos": 0,
                        "ZPos": -1800,
                        "Type": "Model",
                        "Resources": {
                            "ModelResource": {
                                "XRotation": 0,
                                "YRotation": 1024,
                                "ZRotation": 0,
                                "ModelIndex": 2,
                                "TriggerFlag_StartingLock": 0,
                                "SoundIndex": 70,
                                "ActionResource": {
                                    "Position": 0,
                                    "Axis": 0,
                                    "Duration": 0,
                                    "Magnitude": 0,
                                    "NextObjectOffset": 0,
                                    "PreviousObjectOffset": -1,
                                    "NextObjectIndex": 0,
                                    "Flags": 16
                                }
                            }
                        }
                    },
                    {
                        "Position": 17134,
                        "Index": 16,
                        "XPos": -300,
                        "YPos": 0,
                        "ZPos": -1324,
                        "Type": "Model",
                        "Resources": {
                            "ModelResource": {
                                "XRotation": 0,
                                "YRotation": 512,
                                "ZRotation": 0,
                                "ModelIndex": 2,
                                "TriggerFlag_StartingLock": 0,
                                "SoundIndex": 70,
                                "ActionResource": {
                                    "Position": 0,
                                    "Axis": 0,
                                    "Duration": 0,
                                    "Magnitude": 0,
                                    "NextObjectOffset": 0,
                                    "PreviousObjectOffset": -1,
                                    "NextObjectIndex": 0,
                                    "Flags": 16
                                }
                            }
                        }
                    },
                    {
                        "Position": 23505,
                        "Index": 17,
                        "XPos": 0,
                        "YPos": 0,
                        "ZPos": -624,
                        "Type": "Model",
                        "Resources": {
                            "ModelResource": {
                                "XRotation": 0,
                                "YRotation": 512,
                                "ZRotation": 0,
                                "ModelIndex": 2,
                                "TriggerFlag_StartingLock": 0,
                                "SoundIndex": 70,
                                "ActionResource": {
                                    "Position": 0,
                                    "Axis": 0,
                                    "Duration": 0,
                                    "Magnitude": 0,
                                    "NextObjectOffset": 0,
                                    "PreviousObjectOffset": -1,
                                    "NextObjectIndex": 0,
                                    "Flags": 16
                                }
                            }
                        }
                    },
                    {
                        "Position": 20600,
                        "Index": 18,
                        "XPos": -100,
                        "YPos": 0,
                        "ZPos": 100,
                        "Type": "Flat",
                        "Resources": {
                            "FlatResource": {
                                "Position": 20600,
                                "TextureArchive": 199,
                                "TextureRecord": 15,
                                "Flags": 0,
                                "Magnitude": 0,
                                "SoundIndex": 0,
                                "FactionOrMobileId": 512,
                                "NextObjectOffset": 0,
                                "Action": 0,
                                "IsCustomData": false
                            }
                        }
                    },
                    {
                        "Position": 18893,
                        "Index": 19,
                        "XPos": -100,
                        "YPos": 0,
                        "ZPos": 200,
                        "Type": "Flat",
                        "Resources": {
                            "FlatResource": {
                                "Position": 18893,
                                "TextureArchive": 199,
                                "TextureRecord": 15,
                                "Flags": 0,
                                "Magnitude": 0,
                                "SoundIndex": 0,
                                "FactionOrMobileId": 512,
                                "NextObjectOffset": 0,
                                "Action": 0,
                                "IsCustomData": false
                            }
                        }
                    },
                    {
                        "Position": 25549,
                        "Index": 20,
                        "XPos": 200,
                        "YPos": 0,
                        "ZPos": 100,
                        "Type": "Flat",
                        "Resources": {
                            "FlatResource": {
                                "Position": 25549,
                                "TextureArchive": 199,
                                "TextureRecord": 15,
                                "Flags": 0,
                                "Magnitude": 0,
                                "SoundIndex": 0,
                                "FactionOrMobileId": 512,
                                "NextObjectOffset": 0,
                                "Action": 0,
                                "IsCustomData": false
                            }
                        }
                    },
                    {
                        "Position": 24795,
                        "Index": 21,
                        "XPos": -400,
                        "YPos": 0,
                        "ZPos": 300,
                        "Type": "Flat",
                        "Resources": {
                            "FlatResource": {
                                "Position": 24795,
                                "TextureArchive": 199,
                                "TextureRecord": 15,
                                "Flags": 0,
                                "Magnitude": 0,
                                "SoundIndex": 0,
                                "FactionOrMobileId": 512,
                                "NextObjectOffset": 0,
                                "Action": 0,
                                "IsCustomData": false
                            }
                        }
                    },
                    {
                        "Position": 15534,
                        "Index": 22,
                        "XPos": -400,
                        "YPos": 0,
                        "ZPos": 800,
                        "Type": "Flat",
                        "Resources": {
                            "FlatResource": {
                                "Position": 15534,
                                "TextureArchive": 199,
                                "TextureRecord": 15,
                                "Flags": 0,
                                "Magnitude": 0,
                                "SoundIndex": 0,
                                "FactionOrMobileId": 512,
                                "NextObjectOffset": 0,
                                "Action": 0,
                                "IsCustomData": false
                            }
                        }
                    },
                    {
                        "Position": 18717,
                        "Index": 23,
                        "XPos": -200,
                        "YPos": 0,
                        "ZPos": 1200,
                        "Type": "Flat",
                        "Resources": {
                            "FlatResource": {
                                "Position": 18717,
                                "TextureArchive": 199,
                                "TextureRecord": 15,
                                "Flags": 0,
                                "Magnitude": 0,
                                "SoundIndex": 0,
                                "FactionOrMobileId": 512,
                                "NextObjectOffset": 0,
                                "Action": 0,
                                "IsCustomData": false
                            }
                        }
                    },
                    {
                        "Position": 24490,
                        "Index": 24,
                        "XPos": -600,
                        "YPos": 0,
                        "ZPos": 800,
                        "Type": "Flat",
                        "Resources": {
                            "FlatResource": {
                                "Position": 24490,
                                "TextureArchive": 199,
                                "TextureRecord": 15,
                                "Flags": 0,
                                "Magnitude": 0,
                                "SoundIndex": 0,
                                "FactionOrMobileId": 512,
                                "NextObjectOffset": 0,
                                "Action": 0,
                                "IsCustomData": false
                            }
                        }
                    },
                    {
                        "Position": 13046,
                        "Index": 25,
                        "XPos": 0,
                        "YPos": 0,
                        "ZPos": -2000,
                        "Type": "Flat",
                        "Resources": {
                            "FlatResource": {
                                "Position": 13046,
                                "TextureArchive": 199,
                                "TextureRecord": 15,
                                "Flags": 0,
                                "Magnitude": 0,
                                "SoundIndex": 0,
                                "FactionOrMobileId": 512,
                                "NextObjectOffset": 0,
                                "Action": 0,
                                "IsCustomData": false
                            }
                        }
                    }
                ]
            },
            {
                "RdbObjects": null
            },
            {
                "RdbObjects": null
            },
            {
                "RdbObjects": null
            },
            {
                "RdbObjects": null
            },
            {
                "RdbObjects": null
            },
            {
                "RdbObjects": null
            },
            {
                "RdbObjects": null
            },
            {
                "RdbObjects": null
            },
            {
                "RdbObjects": null
            }
        ]
    },
    "RdiBlock": {
        "Data": null
    }
}